wexample_yaml_executor/__init__.py
wexample_yaml_executor-0.0.4.dist-info/METADATA
wexample_yaml_executor-0.0.4.dist-info/WHEEL
wexample_yaml_executor-0.0.4.dist-info/__init__.py
wexample_yaml_executor-0.0.4.dist-info/top_level.txt
wexample_yaml_executor-0.0.4.dist-info/RECORD
